runnable_hub/__init__.py
runnable_hub/common.py
runnable_hub/context.py
runnable_hub/hub.py
runnable_hub/store.py
workers/__init__.py
workers/agentWorker/__init__.py
workers/agentWorker/response.py
workers/agentWorker/worker.py
workers/agentWorker/request/__init__.py
workers/agentWorker/request/agentChainTemplate.py
workers/agentWorker/request/agentDefine.py
workers/agentWorker/request/agentRequest.py
workers/apiWorker/__init__.py
workers/apiWorker/response.py
workers/apiWorker/worker.py
workers/apiWorker/request/__init__.py
workers/apiWorker/request/apiHttpMethod.py
workers/apiWorker/request/apiRequest.py
workers/chainWorker/__init__.py
workers/chainWorker/next.py
workers/chainWorker/response.py
workers/chainWorker/worker.py
workers/chainWorker/request/__init__.py
workers/chainWorker/request/chainFunction.py
workers/chainWorker/request/chainRequest.py
workers/jinjaWorker/__init__.py
workers/jinjaWorker/response.py
workers/jinjaWorker/worker.py
workers/jinjaWorker/request/__init__.py
workers/jinjaWorker/request/jinjaRequest.py
workers/llmWorker/__init__.py
workers/llmWorker/worker.py
workers/llmWorker/request/__init__.py
workers/llmWorker/request/llmMessage.py
workers/llmWorker/request/llmRequest.py
workers/llmWorker/request/llmSetting.py
workers/llmWorker/response/__init__.py
workers/llmWorker/response/llmResponse.py
workers/llmWorker/response/llmUsage.py
workers/processWorker/__init__.py
workers/processWorker/response.py
workers/processWorker/worker.py
workers/processWorker/request/__init__.py
workers/processWorker/request/processJob.py
workers/processWorker/request/processRequest.py
workers/processWorker/request/processStep.py
workers/pythonWorker/__init__.py
workers/pythonWorker/request.py
workers/pythonWorker/response.py
workers/pythonWorker/worker.py
workers/pythonWorker/request/__init__.py
workers/pythonWorker/request/shellRequest.py
workers/shellWorker/__init__.py
workers/shellWorker/response.py
workers/shellWorker/worker.py
runnable_hub-0.3.dist-info/METADATA
runnable_hub-0.3.dist-info/WHEEL
runnable_hub-0.3.dist-info/top_level.txt
runnable_hub-0.3.dist-info/RECORD
