Metadata-Version: 2.1
Name: runnable_hub
Version: 0.3
Summary: Runnable Hub is a middleware for large models, enabling management and execution of complex inference tasks with a flexible architecture and support for multiple task types.
Home-page: https://github.com/alibaba/sreworks-ext/tree/main/runnable-hub
Author: jiongen.zje
Author-email: jiongen.zje@alibaba-inc.com
Classifier: Programming Language :: Python :: 3
Classifier: License :: OSI Approved :: GNU General Public License v2 (GPLv2)
Classifier: Operating System :: OS Independent
Requires-Python: >=3.12
Requires-Dist: pydantic
Requires-Dist: aiohttp
Requires-Dist: jinja2
